pythonpancakes/__init__.py
pythonpancakes/api.py
pythonpancakes-1.0.1.dist-info/LICENSE
pythonpancakes-1.0.1.dist-info/METADATA
pythonpancakes-1.0.1.dist-info/WHEEL
pythonpancakes-1.0.1.dist-info/top_level.txt
pythonpancakes-1.0.1.dist-info/RECORD
