Metadata-Version: 2.1
Name: pythonpancakes
Version: 1.0.1
Summary: A basic request wrapper for the PancakeSwap API
Home-page: https://github.com/scottburlovich/pythonpancakes
Author: Scott Burlovich
Author-email: teedot@gmail.com
License: MIT
Platform: UNKNOWN
Classifier: License :: OSI Approved :: MIT License
Classifier: Programming Language :: Python :: 3
Classifier: Programming Language :: Python :: 3.8
